odoo/addons/odoo_filestore_s3/README.md
odoo/addons/odoo_filestore_s3/__init__.py
odoo/addons/odoo_filestore_s3/__manifest__.py
odoo/addons/odoo_filestore_s3/env_config.py
odoo/addons/odoo_filestore_s3/wrapt_patcher.py
odoo/addons/odoo_filestore_s3/environ_odoo_config/__init__.py
odoo/addons/odoo_filestore_s3/environ_odoo_config/auto_load.py
odoo/addons/odoo_filestore_s3/environ_odoo_config/mapper.py
odoo/addons/odoo_filestore_s3/s3_api/__init__.py
odoo/addons/odoo_filestore_s3/s3_api/adapter.py
odoo/addons/odoo_filestore_s3/s3_api/odoo_s3_fs.py
mangono_addon_odoo_filestore_s3-2.2.0.dist-info/METADATA
mangono_addon_odoo_filestore_s3-2.2.0.dist-info/WHEEL
mangono_addon_odoo_filestore_s3-2.2.0.dist-info/entry_points.txt
mangono_addon_odoo_filestore_s3-2.2.0.dist-info/top_level.txt
mangono_addon_odoo_filestore_s3-2.2.0.dist-info/RECORD
